{
    "ShowEndingMove": true,
    "Names_2": "Player 2",
    "MenuNames_16": "My AI",
    "Names_1": "Player 1",
    "MenuNames_15": "My AI",
    "Names_16": "Player 16",
    "Names_0": "Player 0",
    "MenuNames_14": "My AI",
    "ShowCoordinates": false,
    "MenuNames_13": "My AI",
    "Names_6": "Player 6",
    "Names_13": "Player 13",
    "Names_5": "Player 5",
    "Names_12": "Player 12",
    "Names_4": "Player 4",
    "Names_15": "Player 15",
    "drawInnerVertices": false,
    "Names_3": "Player 3",
    "Names_14": "Player 14",
    "networkPolling": false,
    "drawInnerEdges": false,
    "Names_11": "Player 11",
    "Names_10": "Player 10",
    "MenuNames_12": "My AI",
    "drawInnerCells": false,
    "MenuNames_11": "My AI",
    "MenuNames_10": "My AI",
    "MoveCoord": true,
    "drawOuterEdges": false,
    "PhaseTitle": false,
    "drawMinorVertices": false,
    "alwaysAutoPass": false,
    "drawCornerConvexEdges": false,
    "drawPhasesVertices": false,
    "drawHorizontalEdges": false,
    "SearchTime_8": 1,
    "AI_10": {
        "AI": {"algorithm": "My AI"},
        "constructor": "cannon.runLudii$$Lambda$14/0x0000000840065040@36935fb1"
    },
    "SearchTime_9": 1,
    "AI_11": {
        "AI": {"algorithm": "My AI"},
        "constructor": "cannon.runLudii$$Lambda$14/0x0000000840065040@36935fb1"
    },
    "drawCornerConvexCells": false,
    "SearchTime_6": 1,
    "SearchTime_7": 1,
    "LoadedFromMemory": false,
    "SearchTime_4": 1,
    "SearchTime_5": 1,
    "SearchTime_2": 1,
    "SearchTime_3": 1,
    "SearchTime_15": 1,
    "SearchTime_1": 1,
    "SearchTime_16": 1,
    "CursorTooltip": false,
    "drawOuterCells": false,
    "SearchTime_13": 1,
    "AI_16": {
        "AI": {"algorithm": "My AI"},
        "constructor": "cannon.runLudii$$Lambda$14/0x0000000840065040@36935fb1"
    },
    "NoRepetition": false,
    "SearchTime_14": 1,
    "drawCenterCells": false,
    "SearchTime_11": 1,
    "AI_14": {
        "AI": {"algorithm": "My AI"},
        "constructor": "cannon.runLudii$$Lambda$14/0x0000000840065040@36935fb1"
    },
    "SearchTime_12": 1,
    "AI_15": {
        "AI": {"algorithm": "My AI"},
        "constructor": "cannon.runLudii$$Lambda$14/0x0000000840065040@36935fb1"
    },
    "ShowConnections": false,
    "AI_12": {
        "AI": {"algorithm": "My AI"},
        "constructor": "cannon.runLudii$$Lambda$14/0x0000000840065040@36935fb1"
    },
    "SearchTime_10": 1,
    "AI_13": {
        "AI": {"algorithm": "My AI"},
        "constructor": "cannon.runLudii$$Lambda$14/0x0000000840065040@36935fb1"
    },
    "drawMajorVertices": false,
    "SavedLudLastModifiedTime": "2021-10-23T10:47:18.698732Z",
    "drawCornerConvexVertices": false,
    "drawNeighboursVertices": false,
    "Names_9": "Player 9",
    "Names_8": "Player 8",
    "drawDistanceEdges": false,
    "Names_7": "Player 7",
    "drawBottomVertices": false,
    "drawBottomCells": false,
    "ShowFaceCoordinates": false,
    "RecentGames_2": "/home/elisha/Documents/ISG/Cannon.lud",
    "RecentGames_1": "Tic-Tac-Toe",
    "RecentGames_3": "Surakarta",
    "FrameWidth": 1339,
    "drawSlashEdges": false,
    "drawCornersCells": false,
    "OptionStrings": [],
    "drawLeftEdges": false,
    "drawAngledEdges": false,
    "RecentGames_0": "/home/al/IdeaProjects/cannon2/resources/luds/Cannon.lud",
    "drawDistanceCells": false,
    "drawPerimeterVertices": false,
    "drawBottomEdges": false,
    "editorFontSize": 13,
    "SaveHeuristics": false,
    "drawRadialsCells": false,
    "drawOuterVertices": false,
    "drawMajorCells": false,
    "drawLeftCells": false,
    "drawRadialsVertices": false,
    "VersionNumber": "1.2.10",
    "editorAutocomplete": true,
    "MenuNames_6": "My AI",
    "MenuNames_7": "My AI",
    "MenuNames_8": "My AI",
    "ShowRepetitions": false,
    "drawCenterVertices": false,
    "MenuNames_9": "My AI",
    "savedLudName": "/home/al/IdeaProjects/cannon2/resources/luds/Cannon.lud",
    "FlatBoard": false,
    "ShowFaceIndices": false,
    "coordWithOutline": false,
    "moveSoundEffect": false,
    "ShowPieces": true,
    "ShowAxes": false,
    "moveFormat": "Move",
    "drawRightVertices": false,
    "drawCentreEdges": false,
    "MenuNames_0": "Human",
    "MenuNames_1": "My AI",
    "testLudeme2": "",
    "MenuNames_2": "Random",
    "testLudeme3": "",
    "MenuNames_3": "My AI",
    "MenuNames_4": "My AI",
    "testLudeme1": "",
    "MenuNames_5": "My AI",
    "SwapRule": false,
    "drawNeighboursCells": false,
    "drawTopVertices": false,
    "FrameMaximizedBoth": false,
    "SelectedRuleset": -1,
    "ShowGraph": false,
    "drawSloshEdges": false,
    "showZoomBox": false,
    "ShowIndices": false,
    "ShowEdgeCoordinates": false,
    "FrameHeight": 790,
    "ShowBoard": true,
    "HideAiMoves": true,
    "ShowEdgeIndices": false,
    "testLudeme4": "",
    "drawMajorEdges": false,
    "devMode": false,
    "saveTrialAfterMove": false,
    "CandidateMoves": false,
    "IllegalMoves": false,
    "drawRightEdges": false,
    "drawMinorCells": false,
    "ShowPossibleMoves": true,
    "AI_5": {
        "AI": {"algorithm": "My AI"},
        "constructor": "cannon.runLudii$$Lambda$14/0x0000000840065040@36935fb1"
    },
    "ShowContainerIndices": false,
    "drawPerimeterCells": false,
    "AI_6": {
        "AI": {"algorithm": "My AI"},
        "constructor": "cannon.runLudii$$Lambda$14/0x0000000840065040@36935fb1"
    },
    "AI_3": {
        "AI": {"algorithm": "My AI"},
        "constructor": "cannon.runLudii$$Lambda$14/0x0000000840065040@36935fb1"
    },
    "AI_4": {
        "AI": {"algorithm": "My AI"},
        "constructor": "cannon.runLudii$$Lambda$14/0x0000000840065040@36935fb1"
    },
    "AI_1": {
        "AI": {"algorithm": "My AI"},
        "constructor": "cannon.runLudii$$Lambda$14/0x0000000840065040@36935fb1"
    },
    "AI_2": {"AI": {"algorithm": "Random"}},
    "ShowLastMove": false,
    "NoRepetitionWithinTurn": false,
    "drawCornersVertices": false,
    "drawAxialEdges": false,
    "PuzzleValueSelection": "Automatic",
    "drawDistanceVertices": false,
    "drawTopEdges": false,
    "ShowVertexCoordinates": false,
    "drawPhasesEdges": false,
    "drawRightCells": false,
    "drawCornerConcaveEdges": false,
    "drawMinorEdges": false,
    "drawCornerConcaveVertices": false,
    "drawCornerEdges": false,
    "ShowAIDistribution": false,
    "tabFontSize": 13,
    "ShowCellIndices": false,
    "drawPerimeterEdges": false,
    "FrameLocX": 207,
    "AnimationVisualsType": "None",
    "FrameLocY": 109,
    "networkRefresh": false,
    "startButtonPausesAI": true,
    "TickLength": 0.1,
    "drawSideNumberVertices": 0,
    "drawLeftVertices": false,
    "drawVerticalEdges": false,
    "drawTopCells": false,
    "drawCornerConcaveCells": false,
    "AI_9": {
        "AI": {"algorithm": "My AI"},
        "constructor": "cannon.runLudii$$Lambda$14/0x0000000840065040@36935fb1"
    },
    "drawPhasesCells": false,
    "AI_7": {
        "AI": {"algorithm": "My AI"},
        "constructor": "cannon.runLudii$$Lambda$14/0x0000000840065040@36935fb1"
    },
    "AI_8": {
        "AI": {"algorithm": "My AI"},
        "constructor": "cannon.runLudii$$Lambda$14/0x0000000840065040@36935fb1"
    }
}